{
    "Version": "1.2",
    "Data": {
        "Source": "c:\\users\\islu9578\\documents\\github\\prod\\prod_ue\\intermediate\\build\\win64\\unrealeditor\\inc\\prod_ue\\uht\\prod_ue.init.gen.cpp",
        "ProvidedModule": "",
        "PCH": "c:\\users\\islu9578\\documents\\github\\prod\\prod_ue\\intermediate\\build\\win64\\x64\\prod_ueeditor\\development\\unrealed\\sharedpch.unrealed.project.valapi.cpp20.inclorderoldest.h.pch",
        "Includes": [
            "c:\\users\\islu9578\\documents\\github\\prod\\prod_ue\\intermediate\\build\\win64\\x64\\unrealeditor\\development\\prod_ue\\definitions.prod_ue.h"
        ],
        "ImportedModules": [],
        "ImportedHeaderUnits": []
    }
}